<?xml version="1.0" encoding="UTF-8"?>
<dc><title>*Manzoni, Venezia e il Veneto / a cura di Vittore Branca, Ettore Caccia, Cesare Galimberti. - Firenze : Leo S. Olschki, 1976. - 388, XI p., 1 c. di tav. : ill. ; 24 cm. ((Atti della Tavola rotonda organizzata dalla Fondazione Giorgio Cini e dall'Istituto veneto di scienze, lettere ed arti a Venezia nel 1973.</title>
<subject>MANZONI, ALESSANDRO - Congressi - Venezia - 1973</subject><subject>Congressi - Venezia - 1973</subject><subject>Manzoni, Alessandro - Veneto - Congressi - 1973</subject>
<contributor>Branca, Vittore</contributor><contributor>Caccia, Ettore</contributor><contributor>*Fondazione *Giorgio *Cini</contributor><contributor>Galimberti, Cesare</contributor>
<contributor>*Istituto *veneto di *scienze, *lettere ed arti</contributor><contributor>*Tavola-*rotonda sul *tema *Manzoni, Venezia e il Veneto &lt;1973 ; Venezia&gt;</contributor>
<date>1976</date><type>Testo a stampa (moderno)</type><identifier>DUC-VEA-213800</identifier><identifier>SBL0593421</identifier><language>ITA</language>
<relation>Titolo="*Civiltà veneziana. Saggi. - Venezia [etc.] : Istituto per la collaborazione culturale ; [poi] Firenze : L. S. Olschki, 1956-. ((BNI febbraio 1994." Relationship="FA PARTE DI"</relation>
<imgpagestart n="7" type="arab">2</imgpagestart>
<imgindex>193-194</imgindex>
<sub2>Cultura - Venezia; XIX</sub2>
<scan>major problems</scan>
<operator>Martina Babetto</operator>
<provenance>BAUM</provenance></dc>