<?xml version="1.0" encoding="UTF-8"?>
<dc><title>*Hadriatica : attorno a Venezia e al Medioevo tra arti, storia e storiografia : scritti in onore di Wladimiro Dorigo / a cura di Ennio Concina, Giordana Trovabene, Michela Agazzi. - Padova : Il Poligrafo, 
[2002]. - 405 p. : ill. ; 24 cm.</title><subject>Arte - Raccolte di saggi</subject><subject>ARTE - Saggi</subject><subject>DORIGO, WLADIMIRO - Celebrazioni</subject>
<subject>Dorigo, Wladimiro &lt;1927-&gt;</subject><contributor>Agazzi, Michela</contributor><contributor>Concina, Ennio</contributor><contributor>Dorigo, Wladimiro</contributor>
<contributor>Trovabene, Giordana</contributor><date>2002</date><type>Testo a stampa (moderno)</type><identifier>DUC-VEA-162232</identifier><identifier>VEA0150679</identifier>
<language>ITA</language><relation>Titolo="*Miscellanea. - Padova : Il poligrafo." Relationship="FA PARTE DI"</relation>
<relation>Titolo="*Restaurando le fronti : novita e conferme dai lavori alle facciate medioevali di Palazzo Ducale / Giandomenico Romanelli" Relationship="FA PARTE DI"</relation>
<imgindex>2-4</imgindex>
<imgpagestart n="9" type="arab">4</imgpagestart>
<scan>major problems</scan>
<operator>Silvia Ferronato</operator>
<provenance>BAUM</provenance></dc>