<?xml version="1.0" encoding="UTF-8"?>
<dc><title>*Studi di storia economica veneziana / Gino Luzzatto. - Padova : CEDAM, 1954. - VI, 310 p. ; 25 cm. ((In testa al front.: Istituto universitario di economia e commercio, Venezia.</title>
<creator>Luzzatto, Gino</creator><subject>VENEZIA &lt;REPUBBLICA&gt; - Economia</subject><subject>Storia economica</subject><date>1954</date><type>Testo a stampa (moderno)</type>
<identifier>DUC-VEA-681223</identifier><identifier>NAP0092304</identifier><language>ITA</language>
<imgindex>157-158</imgindex>
<imgpagestart n="2" type="arab">4</imgpagestart>
<sub2>Economia - Storia - Raccolte di saggi</sub2>
<scan>minor problems</scan>
<operator>Martina Babetto</operator>
<provenance>BAUM</provenance></dc>