<?xml version="1.0" encoding="UTF-8"?>
<dc><title>L'*opera di Giovanni Bordiga nel risveglio culturale di Venezia tra fine Ottocento e inizio Novecento : atti della Giornata di studi, Venezia, Ateneo veneto, 16 novembre 2012 / a cura di Guido Zucconi. - Venezia : Ateneo veneto, 2014. - 214 p. : ill. con [4] carte di tav. ; 24 cm</title>
<subject>Bordiga, Giovanni &lt;1854-1933&gt; - Congressi - Venezia - 2012</subject><contributor>*Ateneo *Veneto</contributor><contributor>Zucconi, Guido</contributor>
<date>2014</date><type>Testo a stampa (moderno)</type><identifier>DUC-VEA-2409713</identifier><identifier>PUV1397060</identifier><language>ITA</language>
<relation>Titolo="*Ricerche storiche. - Venezia : Ateneo veneto : [poi] Marsilio." Relationship="FA PARTE DI"</relation>
<relation>Titolo="*Ateneo veneto : *Atti e memorie dell'Ateneo veneto : rivista mensile di scienze, lettere ed arti. - Ser. 4., n. 1 (giu. 1881)-    . - Venezia : M. Fontana, 1881-. -   v. ; 24 cm. ((Bimestrale dal 1896. - La periodicità varia. - Dal 1916 l'editore varia in: Ateneo veneto. - Sospeso dal 1927 al 1930 e dal 1946 al 1948." Relationship="SUPPLEMENTO DI"</relation>
<relation>Titolo="Il *promotore delle Biennali d'arte / Anna Mazzanti." Relationship="FA PARTE DI"</relation>
<imgpagestart n="10" type="arab">5</imgpagestart>
<imgindex>3</imgindex>
<sub2>Cultura - Venezia; XIX-XX</sub2>
<scan>minor problems</scan>
<operator>Martina Babetto</operator>
<provenance>BAUM</provenance></dc>