{
  "@context": "https://w3id.org/oc/corpus/context.json",
  "@graph": [
    {
      "a": "metadata_snapshot",
      "generated": "2020-03-25T16:13:52.775740",
      "generated_by": "https://w3id.org/oc/corpus/br/0120119/prov/ca/1",
      "iri": "https://w3id.org/oc/corpus/br/0120119/prov/se/1",
      "label": "snapshot entity metadata 1 related to bibliographic resource 119 [se/1 -> br/0120119]",
      "snapshot_of": "gbr:0120119",
      "source": "bogus-url"
    },
    {
      "a": "metadata_snapshot",
      "generated": "2020-03-25T16:13:52.722965",
      "generated_by": "https://w3id.org/oc/corpus/br/0120115/prov/ca/1",
      "iri": "https://w3id.org/oc/corpus/br/0120115/prov/se/1",
      "label": "snapshot entity metadata 1 related to bibliographic resource 115 [se/1 -> br/0120115]",
      "snapshot_of": "gbr:0120115",
      "source": "bogus-url"
    },
    {
      "a": "metadata_snapshot",
      "generated": "2020-03-25T16:13:52.665098",
      "generated_by": "https://w3id.org/oc/corpus/br/0120111/prov/ca/1",
      "iri": "https://w3id.org/oc/corpus/br/0120111/prov/se/1",
      "label": "snapshot entity metadata 1 related to bibliographic resource 111 [se/1 -> br/0120111]",
      "snapshot_of": "gbr:0120111",
      "source": "bogus-url"
    },
    {
      "a": "metadata_snapshot",
      "generated": "2020-03-25T16:13:52.766269",
      "generated_by": "https://w3id.org/oc/corpus/br/0120118/prov/ca/1",
      "iri": "https://w3id.org/oc/corpus/br/0120118/prov/se/1",
      "label": "snapshot entity metadata 1 related to bibliographic resource 118 [se/1 -> br/0120118]",
      "snapshot_of": "gbr:0120118",
      "source": "bogus-url"
    },
    {
      "a": "metadata_snapshot",
      "generated": "2020-03-25T16:13:52.732706",
      "generated_by": "https://w3id.org/oc/corpus/br/0120116/prov/ca/1",
      "iri": "https://w3id.org/oc/corpus/br/0120116/prov/se/1",
      "label": "snapshot entity metadata 1 related to bibliographic resource 116 [se/1 -> br/0120116]",
      "snapshot_of": "gbr:0120116",
      "source": "bogus-url"
    },
    {
      "a": "metadata_snapshot",
      "generated": "2020-03-25T16:13:52.703617",
      "generated_by": "https://w3id.org/oc/corpus/br/0120114/prov/ca/1",
      "iri": "https://w3id.org/oc/corpus/br/0120114/prov/se/1",
      "label": "snapshot entity metadata 1 related to bibliographic resource 114 [se/1 -> br/0120114]",
      "snapshot_of": "gbr:0120114",
      "source": "bogus-url"
    },
    {
      "a": "metadata_snapshot",
      "generated": "2020-03-25T16:13:52.742026",
      "generated_by": "https://w3id.org/oc/corpus/br/0120117/prov/ca/1",
      "iri": "https://w3id.org/oc/corpus/br/0120117/prov/se/1",
      "label": "snapshot entity metadata 1 related to bibliographic resource 117 [se/1 -> br/0120117]",
      "snapshot_of": "gbr:0120117",
      "source": "bogus-url"
    },
    {
      "a": "metadata_snapshot",
      "generated": "2020-03-25T16:13:52.673685",
      "generated_by": "https://w3id.org/oc/corpus/br/0120112/prov/ca/1",
      "iri": "https://w3id.org/oc/corpus/br/0120112/prov/se/1",
      "label": "snapshot entity metadata 1 related to bibliographic resource 112 [se/1 -> br/0120112]",
      "snapshot_of": "gbr:0120112",
      "source": "bogus-url"
    },
    {
      "a": "metadata_snapshot",
      "generated": "2020-03-25T16:13:52.683514",
      "generated_by": "https://w3id.org/oc/corpus/br/0120113/prov/ca/1",
      "iri": "https://w3id.org/oc/corpus/br/0120113/prov/se/1",
      "label": "snapshot entity metadata 1 related to bibliographic resource 113 [se/1 -> br/0120113]",
      "snapshot_of": "gbr:0120113",
      "source": "bogus-url"
    }
  ]
}