<?xml version="1.0" encoding="UTF-8"?>
<dc><title>La *Pieta a Venezia : arte, musica e cura dell'infanzia fra tradizione e innovazione / a cura di Antonio Tommaseo Ponzetta ... [et al.]. - Venezia : Istituto Provinciale per l'Infanzia "Santa Maria della Pieta", 2008. - 189 p. : ill. ; 32 cm.</title>
<subject>VENEZIA - Chiesa di Santa Maria della Pieta</subject><subject>CHIESA DI SANTA MARIA DELLA PIETA</subject><subject>VENEZIA - Istituto della Pieta - Storia</subject>
<subject>ISTITUTO DELLA PIETA</subject><subject>Venezia - Attività assistenziali - Storia</subject><contributor>Tommaseo Ponzetta, Antonio</contributor><date>2008</date>
<type>Testo a stampa (moderno)</type><identifier>DUC-VEA-670911</identifier><identifier>VEA0985674</identifier><language>ITA</language>
<imgpagestart n="23" type="arab">11</imgpagestart>
<imgbib>91-93</imgbib>
<sub2>Storia sociale - Venezia</sub2>
<scan>flawless</scan>
<operator>Martina Babetto</operator>
<provenance>BAUM</provenance></dc>