<?xml version="1.0" encoding="UTF-8"?>
<dc><title>Le *migrazioni da e per Venezia insulare / Gabriele Zanetto, Fabio Lando. - Pordenone : Grafiche Editoriali Artistiche Pordenonesi, 1978. - 327-330 (4) p. ; 24 cm. ((Estratto da : Convegno di Studi sui fenomeni migratori in Italia (Piancavallo 28-30 aprile 1978)</title>
<creator>Zanetto, Gabriele</creator><subject>Venezia</subject><subject>MIGRAZIONI</subject><date>1978</date><type>Testo a stampa (moderno)</type>
<identifier>DUC-VEA-1496822</identifier><identifier>VEA1072633</identifier><language>ITA</language>
<imgpagestart n="327" type="arab">1</imgpagestart>
<sub2>Venezia - Storia</sub2>
<scan>major problems</scan>
<operator>Martina Babetto</operator>
<provenance>BAUM</provenance></dc>