<?xml version="1.0" encoding="UTF-8"?>
<dc><title>*Manin and the Venetian revolution of 1848 / by George Macaulay Trevelyan. - London : Longmans. Green and co., 1923. - XV, 284 p., \16! c. di tav. : ill., c. geogr. ; 22 cm.</title><creator>Trevelyan, George Macaulay</creator>
<subject>VENEZIA - Storia - 1848</subject><subject>Manin, Daniele - Attivita politica</subject><subject>Venezia - Rivoluzione - 1848-49</subject><subject>Venezia - Storia moderna</subject><subject>Manin, Daniele (1804-57) ; uomo politico veneziano</subject>
<date>1923</date><type>Testo a stampa (moderno)</type><identifier>DUC-VEA-546410</identifier><identifier>IEI0159234</identifier><language>ENG</language>
<imgpagestart n="7" type="roman">3</imgpagestart>
<imgpagestart n="3" type="arab">9</imgpagestart>
<imgbib>152-160</imgbib>
<sub2> Manin , Daniele - Storia - Venezia ; XIX</sub2>
<operator>Martina Babetto</operator>
<provenance>BAUM</provenance></dc>