<?xml version="1.0" encoding="UTF-8"?>
<dc><title>*Ca' Albrizzi di Sant'Aponal / Ileana Chiappini di Sorio. - Venezia : Centro internazionale della grafica, [1997]. - 69 p., 1 c. di tav. ripieg. : ill. ; 24 cm.</title>
<creator>Chiappini Di Sorio, Ileana</creator><subject>VENEZIA - Palazzo Albrizzi</subject><subject>Venezia - Ca' Albrizzi</subject><date>1997</date><type>Testo a stampa (moderno)</type>
<identifier>DUC-VEA-51030</identifier><identifier>VEA0097396</identifier><language>ITA</language>
<imgpagestart n="5" type="arab">3</imgpagestart>
<imgbib>31-35</imgbib>
<sub2>Chiese - Venezia</sub2>
<scan>flawless</scan>
<operator>Martina Babetto</operator>
<provenance>BAUM</provenance></dc>