<?xml version="1.0" encoding="UTF-8"?>
<dc><title>La *navigazione veneziana nel Mar Nero 13.-15. sec. / Sergej P. Karpov. - Ravenna, Edizioni del Girasole, stampa 2000. - 202 p. ; 24 cm. ((Trad. di Giovanni Fanti e Marina Bakhmatova.</title>
<creator>Karpov, Sergej Pavlovic</creator><subject>COMMERCIO MARITTIMO - Venezia &lt;Repubblica&gt; - Sec. 13.-15.</subject><subject>COMMERCIO MARITTIMO - Mar Nero - Sec. 13.-15.</subject>
<date>2000</date><type>Testo a stampa (moderno)</type><identifier>DUC-VEA-238073</identifier><identifier>RAV0653152</identifier><language>ITA</language>
<relation>Titolo="*Girasole documenti. - Ravenna : Edizioni del Girasole." Relationship="FA PARTE DI"</relation>
<imgpagestart n="7" type="arab">3</imgpagestart>
<sub2>Commercio [e] Navigazione - Mar Nero</sub2>
<scan>flawless</scan>
<operator>Martina Babetto</operator>
<provenance>BAUM</provenance></dc>