<?xml version="1.0" encoding="UTF-8"?>
<dc><title>The *sacred vocal music of Antonio Vivaldi / Michael Talbot. - Firenze : L. S. Olschki, 1995. - XI, 565 p., [4] c. di tav. ; 24 cm. ((Seguono appendici. - In testa al front.: Fondazione Giorgio Cini;
 Istituto italiano Antonio Vivaldi, Venezia.</title><creator>Talbot, Michael  &lt;1943-    &gt;</creator><subject>MUSICA SACRA</subject><subject>VIVALDI, ANTONIO</subject>
<subject>MUSICA SACRA - Venezia - Sec. 17.-18.</subject><subject>VIVALDI, ANTONIO</subject><subject>Vivaldi, Antonio &lt;1678-1741.&gt;</subject><date>1995</date>
<type>Testo a stampa (moderno)</type><identifier>DUC-VEA-314787</identifier><identifier>VEA0077516</identifier><language>ENG</language><relation>Titolo="*Studi di musica 
 veneta. Quaderni vivaldiani. - Firenze : L. S. Olschki, 1980-" Relationship="FA PARTE DI"</relation>
<imgpagestart n="5" type="roman">2</imgpagestart>
<imgpagestart n="1" type="arab">6</imgpagestart>
<sub2>Venezia - musica; XVII-XVIII</sub2>
<imgbib>277-282</imgbib>
<scan>minor problems</scan>
<operator>Silvia Ferronato</operator>
<provenance>BAUM</provenance></dc>