<?xml version="1.0" encoding="UTF-8"?>
<dc><title>*Benedetto chi ti porta, maledetto chi ti manda : l'infanzia abbandonata nel Triveneto, secoli 15.-19. / a cura di Casimira Grandi. - Treviso : Fondazione Benetton studi ricerche : 
Canova, 1997 (stampa 1998). - XIV, 349 p. : ill. ; 24 cm.</title><subject>OSPEDALE DELLA PIETA</subject><subject>FANCIULLI ABBANDONATI - Veneto - Sec. 15.-19.</subject>
<subject>ISTITUTI DI ASSISTENZA E DI BENEFICENZA - Veneto - Sec. 15.-19.</subject><subject>INFANZIA ABBANDONATA - Italia - Sec. 15.-19.</subject>
<subject>Fanciulli abbandonati - Assistenza - Venezia</subject><contributor>Grandi, Casimira</contributor><date>1997</date><type>Testo a stampa (moderno)</type>
<identifier>DUC-VEA-38393</identifier><identifier>PUV0368541</identifier><language>ITA</language>
<relation>Titolo="*Studi veneti. - Venezia : Il cardo ; Treviso : Fondazione Benetton. ((Collezione numerata o meno." Relationship="FA PARTE DI"</relation>
<imgindex>2-3</imgindex>
<imgpagestart n="6" type="roman">3</imgpagestart>
<imgpagestart n="3" type="arab">8</imgpagestart>
<sub2>storia sociale - Veneto;XV-XIX</sub2>
<operator>Silvia Ferronato</operator>
<provenance>BAUM</provenance></dc>