<?xml version="1.0" encoding="UTF-8"?>
<dc><title>The *Venetian patriciate : reality versus myth / Donald E. Queller. - Urbana ; Chicago : University of Illinois press, c1986. - XIII, 386 p. ; 24 cm</title><creator>Queller, Donald E.</creator>
<subject>NOBILTA</subject><subject>VENEZIA - Storia</subject><subject>Venezia - Nobiltà - Sec. 7.-16.</subject><date>1986</date><type>Testo a stampa (moderno)</type>
<identifier>DUC-VEA-1086567</identifier><identifier>TO00066105</identifier><language>ENG</language>
<imgbib>137-177 ; 181-193</imgbib>
<imgpagestart n="9" type="roman">4</imgpagestart>
<imgpagestart n="3" type="arab">8</imgpagestart>
<sub2>Aristocrazia - Venezia ; VII-XVI</sub2>
<scan>minor problems</scan>
<operator>Martina babetto</operator>
<provenance>BAUM</provenance></dc>