<?xml version="1.0" encoding="UTF-8"?>
<dc><title>Le *chiese di Venezia / Umberto Franzoi, Dina Di Stefano. - [S.l.] : Alfieri, [1976]. - LXIV, 549 p. : ill. ; 32 cm.</title><creator>Franzoi, Umberto</creator><subject>VENEZIA - Storia ecclesiastica</subject>
<subject>STORIA ECCLESIASTICA</subject><subject>Architettura</subject><subject>VENEZIA - Chiese</subject><subject>CHIESE</subject><subject>Venezia-chiese</subject>
<subject>Chiese - Venezia - Storia</subject><subject>Chiese veneziane</subject><date>1976</date><type>Testo a stampa (moderno)</type><identifier>DUC-VEA-64933</identifier>
<identifier>VEA0016377</identifier><language>ITA</language>
<imgpagestart n="9" type="roman">5</imgpagestart>
<imgpagestart n="11" type="arab">34</imgpagestart>
<imgbib>209-302</imgbib>
<operator>Silvia Ferronato</operator>
<scan>major problems</scan>
<provenance>BAUM</provenance></dc>