<?xml version="1.0" encoding="UTF-8"?>
<dc><title>*Saggi di storia del diritto commerciale / Giovanni Cassandro. - Napoli : Edizioni scientifiche italiane, stampa 1974. - VII, 427 p. ; 24 cm. ((A cura di Cesare Maria Moschetti.</title>
<creator>Cassandro, Giovanni</creator><subject>DIRITTO COMMERCIALE</subject><contributor>Moschetti, Cesare Maria</contributor><date>1974</date><type>Testo a stampa (moderno)</type>
<identifier>DUC-VEA-2412699</identifier><identifier>SBL0563983</identifier><language>ITA</language>
<imgpagestart n="5" type="roman">2</imgpagestart>
<imgpagestart n="1" type="arab">4</imgpagestart>
<scan>minor problems</scan>
<operator>Silvia Ferronato</operator>
<provenance>BAUM</provenance></dc>