<?xml version="1.0" encoding="UTF-8"?>
<dc><title>3.1. - Vicenza : N. Pozza, °1980!. - XV, 654 p., °36! c. di tav. : ill. ; 28 cm.</title><subject>VENETO - Storia</subject><date>1980</date><type>Testo a stampa (moderno)</type>
<identifier>DUC-VEA-92532</identifier><identifier>FER0123415</identifier><language>ITA</language><relation>Titolo="3: *Dal primo Quattrocento al Concilio di Trento" Relationship="FA PARTE DI"</relation>
<sub2>Cultura - Veneto - Storia ; XV-XVI</sub2>
<imgpagestart n="14" type="roman">6</imgpagestart>
<imgpagestart n="2" type="arab">8</imgpagestart>
<scan>flawless</scan>
<operator>Martina Babetto</operator>
<provenance>BAUM</provenance></dc>