<?xml version="1.0" encoding="UTF-8"?>
<dc><title>La *Scuola Grande di San Rocco a Venezia / a cura di Franco Posocco e Salvatore Settis ; scritti di Victoria Avery ... [et al.] ; fotografie di Cameraphoto Arte, Venezia. - Modena : Franco Cosimo Panini, 2008. - 2 v. : ill. ; 33 cm. 
((Front. e parti dei testi anche in inglese. - In custodia.</title><subject>SCUOLA DI SAN ROCCO</subject><subject>VENEZIA - Scuola Grande di San Rocco</subject><contributor>Avery, Victoria</contributor>
<contributor>Posocco, Franco</contributor><contributor>Settis, Salvatore</contributor><contributor>*Cameraphoto *Arte &lt;Venezia&gt;</contributor><date>2008</date><type>Testo a stampa (moderno)</type>
<identifier>DUC-VEA-481801</identifier><identifier>VEA0789718</identifier><language>ITA</language><relation>Titolo="*Mirabilia Italiæ. - Modena : F. C. Panini." Relationship="FA PARTE DI"</relation>
<relation>Titolo="The *Scuola Grande di San Rocco in Venice." Relationship="HA PER ALTRO TITOLO"</relation><relation>Titolo="[1]: *Testi. - Modena : Francesco Cosimo Panini, 2008. - 396 p. : ill. ; 32 cm." Relationship="FA PARTE DI"</relation>
<relation>Titolo="[2]: *Atlante. - Modena : Franco Cosimo Panini, [2008]. - 371 p., [4] c. ripieg. : ill. ; 32 cm. ((Tit. del deorso. - Front. e testo anche in inglese." Relationship="FA PARTE DI"</relation>
<relation>Titolo="[1]: *Testi. - Modena : Franco Cosimo Panini, [2008]. - 396 p. : ill. ; 32 cm. ((Tit. del dorso. - Front. anche in inglese." Relationship="FA PARTE DI"</relation>
<imgpagestart n="9" type="arab">4</imgpagestart>
<imgbib>180-195</imgbib>
<operator>Silvia Ferronato</operator>
<provenance>BAUM</provenance></dc>