<?xml version="1.0" encoding="UTF-8"?>
<dc><title>*Paesi e mari ignoti : America e colonialismo europeo nella cultura veneziana, secoli 16.-17. / Federica Ambrosini. - Venezia : Deputazione di storia patria per le Venezie, 1982. - VI, 308 p. ; 25 cm.</title>
<creator>Ambrosini, Federica</creator><subject>VENEZIA &lt;REPUBBLICA&gt; - Relazioni con l'America - Sec. 16.-17.</subject><subject>Colonialismo europeo - America - Sec. 16.-17.</subject><date>1982</date>
<type>Testo a stampa (moderno)</type><identifier>DUC-VEA-257633</identifier><identifier>SBL0608628</identifier><language>ITA</language>
<relation>Titolo="*Miscellanea di studi e memorie. - Venezia : Deputazione di storia patria per le Venezie, 1933-." Relationship="FA PARTE DI"</relation>
<imgpagestart n="6" type="roman">3</imgpagestart>
<imgpagestart n="4" type="arab">5</imgpagestart>
<sub2>Venezia - Rapporti [con l'] America ; XVI-XVII</sub2>
<scan>flawless</scan>
<operator>Martina Babetto</operator>
<provenance>BAUM</provenance></dc>