<?xml version="1.0" encoding="UTF-8"?>
<dc><title>*Celebrazione e autocritica: la Serenissima e la ricerca dell'identità veneziana nel tardo Cinquecento / a cura di Benjamin Paul. - Roma : Viella ; Venezia : Centro tedesco di studi veneziani, 2014. - 320 p., [32] carte di tav. : ill. ; 21 cm. 
((Relazioni presentate al Convegno tenuto a Venezia nel 2006. - Testo in italiano o inglese</title><subject>Venezia &lt;Repubblica&gt; - 1560-1600 - Congressi - Venezia - 2006</subject>
<subject>Biblioteca nazionale Marciana - Ms. It. VII, 4 - Citazione bibliografica</subject><subject>Biblioteca nazionale Marciana - Ms. It. VII, 5 - Citazione bibliografica</subject>
<subject>Biblioteca nazionale Marciana - Ms. It. VII, 417 - Citazione bibliografica</subject><subject>Biblioteca nazionale Marciana - Ms. It. VII, 227 - Citazione bibliografica</subject>
<subject>Biblioteca nazionale Marciana - Ms. It. VII, 364 - Citazione bibliografica</subject><subject>Biblioteca nazionale Marciana - Ms. It. VII, 134 - Citazione bibliografica</subject>
<subject>Biblioteca nazionale Marciana - Ms. It. VII, 224 - Citazione bibliografica</subject><subject>Biblioteca nazionale Marciana - Ms. It. VII, 110 - Citazione bibliografica</subject>
<subject>Biblioteca nazionale Marciana - Ms. It. VII, 336 - Citazione bibliografica</subject><contributor>Paul, Benjamin</contributor><date>2014</date><type>Testo a stampa (moderno)</type>
<identifier>DUC-VEA-2375585</identifier><identifier>VEA1129216</identifier><language>ITA</language>
<relation>Titolo="*Venetiana / Centro tedesco di studi veneziani. - Roma : Edizioni di storia e letteratura ; Venezia : Centro tedesco di studi veneziani ; [poi] Roma : Viella, 2004-" Relationship="FA PARTE DI"</relation>
<relation>Titolo="*Celebrazione e autocritica" Relationship="HA PER ALTRO TITOLO"</relation>
<imgpagestart n="6" type="arab">3</imgpagestart>
<imgbib>174-192</imgbib>
<imgindex>2-3</imgindex>
<scan>minor problems</scan>
<operator>Silvia Ferronato</operator>
<provenance>BAUM</provenance></dc>