<?xml version="1.0" encoding="UTF-8"?>
<dc><title>*Building Renaissance Venice : patrons, architects and builders, c. 1430-1500 / Richard J. Goy. - New Haven ; London : Yale University Press, c2006. - 316 p. : ill. ; 29 cm.</title>
<creator>Goy, Richard J.</creator><subject>ARCHITETTURA - Venezia - Sec. 16.</subject><subject>Architettura - Venezia - Storia - Sec.15</subject><date>2006</date>
<type>Testo a stampa (moderno)</type><identifier>DUC-VEA-49718</identifier><identifier>VEA0207312</identifier><language>ENG</language>
<imgbib>155-158</imgbib>
<imgpagestart n="7" type="roman">3</imgpagestart>
<imgpagestart n="1" type="arab">5</imgpagestart>
<sub2>Architettura - Venezia ; XV-XVI</sub2>
<scan>flawless</scan>
<operator>Martina Babetto</operator>
<provenance>BAUM</provenance></dc>