<?xml version="1.0" encoding="UTF-8"?>
<dc><title>*Culture e lingue nel Veneto medievale / Gianfranco Folena. - Padova : Editoriale Programma, [1990]. - XIX, 412 p., 22 p. di tav. : ill. ; 24 cm.</title><creator>Folena, Gianfranco</creator><subject>MEDIOEVO</subject><subject>VENETO - Cultura - Sec. 5.-15.</subject><subject>LETTERATURA ITALIANA - Veneto - Sec. 5.-15.</subject><subject>DIALETTI VENETI - Sec. 5.-15.</subject><subject>VENETO - Cultura</subject><subject>ONOMASTICA</subject><subject>LINGUISTICA VENETA</subject><subject>LINGUA - Sec. 12.-13.</subject><subject>COGNOMI VENEZIANI</subject><subject>Veneto</subject><subject>Veneto - Lingua - Medioevo</subject><subject>Veneto - Cultura - Medioevo</subject><subject>Veneto - Lingua</subject><subject>Veneto - Storia medievale</subject><subject>Linguistica</subject><date>1990</date><type>Testo a stampa (moderno)</type><identifier>DUC-VEA-89272</identifier><identifier>MIL0075687</identifier><language>ITA</language><relation>Titolo="*Filologia veneta. Testi e studi. - Padova : Programma : \poi! Esedra, 1990-." Relationship="FA PARTE DI"</relation>
<imgpagestart n="8" type="roman">139</imgpagestart>
<imgpagestart n="2" type="arab">147</imgpagestart>
<imgindex>138-139</imgindex>
<scan>minor problems</scan>
<operator>Silvia Ferronato</operator>
<provenance>BAUM</provenance></dc>