<?xml version="1.0" encoding="UTF-8"?>
<dc><title>*Cultura francese e censura a Venezia nel secondo Settecento : ricerche storico-bibliografiche / Franco Piva. - Venezia : Istituto veneto di scienze lettere ed arti, 1973. - 221 p., 2 c. di tav. : ill. ; 24 cm. ((Memoria presentata dal m. e. prof. Diego Valeri nell'adunanza ordinaria dl 25 novembre 1972</title>
<creator>Piva, Franco  &lt;1942-   &gt;</creator><subject>Censura di stampa - Venezia (Repubblica) - Sec. 18.</subject><subject>Censura - Venezia - Sec. 18.</subject>
<date>1973</date><type>Testo a stampa (moderno)</type><identifier>DUC-VEA-512019</identifier><identifier>PUV0204378</identifier><language>ITA</language>
<relation>Titolo="*Memorie. Classe di scienze morali, lettere ed arti / Istituto veneto di scienze, lettere ed arti Venezia. - Vol. 34, fasc. 2 (1966)- . - Venezia : Presso la sede dell'Istituto veneto, 1966-. - v. ; 24 cm. ((Periodicità non determinata. - N. monografici. - Non pubblicato nel 2003." Relationship="FA PARTE DI"</relation>
<imgpagestart n="7" type="arab">4</imgpagestart>
<sub2>Cultura - Venezia; XVIII</sub2>
<scan>minor problems</scan>
<operator>Martina Babetto</operator>
<provenance>BAUM</provenance></dc>